keysymdef.py
keysymdef-1.1.0.dist-info/METADATA
keysymdef-1.1.0.dist-info/WHEEL
keysymdef-1.1.0.dist-info/top_level.txt
keysymdef-1.1.0.dist-info/RECORD
