Metadata-Version: 2.1
Name: keysymdef
Version: 1.1.0
Summary: X11 keysym data for Python
Home-page: https://github.com/barneygale/keysymdef
Author: Barney Gale
License: X11
Platform: UNKNOWN
